timedctl/__init__.py
timedctl/cli.py
timedctl/helpers.py
timedctl/timedctl.py
timedctl-5.9.2.dist-info/LICENSE
timedctl-5.9.2.dist-info/METADATA
timedctl-5.9.2.dist-info/WHEEL
timedctl-5.9.2.dist-info/entry_points.txt
timedctl-5.9.2.dist-info/RECORD
