Metadata-Version: 2.1
Name: timedctl
Version: 5.9.2
Summary: CLI for timed
License: AGPL-3.0-only
Author: Arthur Deierlein
Author-email: arthur.deierlein@adfinis.com
Requires-Python: >=3.11,<4.0
Classifier: License :: OSI Approved :: GNU Affero General Public License v3
Classifier: Programming Language :: Python :: 3
Classifier: Programming Language :: Python :: 3.11
Classifier: Programming Language :: Python :: 3.12
Requires-Dist: click (>=8.1.3,<9.0.0)
Requires-Dist: click-aliases (>=1.0.1,<2.0.0)
Requires-Dist: libtimed (>=0.6.4,<0.7.0)
Requires-Dist: pyfzf (>=0.3.1,<0.4.0)
Requires-Dist: rich (>=13.4.2,<14.0.0)
Requires-Dist: tomlkit (>=0.11.8,<0.13.0)
